uber_compose/__init__.py
uber_compose/uber_compose.py
uber_compose/version
uber_compose/version.py
uber_compose/core/__init__.py
uber_compose/core/constants.py
uber_compose/core/docker_compose.py
uber_compose/core/sequence_run_types.py
uber_compose/core/system_docker_compose.py
uber_compose/core/docker_compose_shell/__init__.py
uber_compose/core/docker_compose_shell/interface.py
uber_compose/core/docker_compose_shell/types.py
uber_compose/core/utils/__init__.py
uber_compose/core/utils/compose_files.py
uber_compose/core/utils/compose_instance_cfg.py
uber_compose/core/utils/env_files.py
uber_compose/core/utils/process_command_output.py
uber_compose/core/utils/shell_process.py
uber_compose/core/utils/state_waiting.py
uber_compose/env_description/__init__.py
uber_compose/env_description/env_tools.py
uber_compose/env_description/env_types.py
uber_compose/errors/__init__.py
uber_compose/errors/migrations.py
uber_compose/errors/up.py
uber_compose/helpers/__init__.py
uber_compose/helpers/broken_services.py
uber_compose/helpers/bytes_pickle.py
uber_compose/helpers/countdown_counter.py
uber_compose/helpers/exec_record.py
uber_compose/helpers/exec_result.py
uber_compose/helpers/health_policy.py
uber_compose/helpers/jobs_result.py
uber_compose/helpers/labels.py
uber_compose/helpers/singleton.py
uber_compose/helpers/state_keeper.py
uber_compose/output/__init__.py
uber_compose/output/console.py
uber_compose/output/styles.py
uber_compose/utils/__init__.py
uber_compose/utils/docker_compose_files_path.py
uber_compose/utils/docker_compose_service_deps.py
uber_compose/utils/search_docker_compose_files.py
uber_compose/utils/services_construction.py
uber_compose/vedro_plugin/__init__.py
uber_compose/vedro_plugin/plugin.py
uber_compose/vedro_plugin/base_structures/__init__.py
uber_compose/vedro_plugin/base_structures/common_json_cli.py
uber_compose/vedro_plugin/helpers/__init__.py
uber_compose/vedro_plugin/helpers/scenario_ordering.py
uber_compose-2.1.4.dist-info/licenses/LICENSE
uber_compose-2.1.4.dist-info/METADATA
uber_compose-2.1.4.dist-info/WHEEL
uber_compose-2.1.4.dist-info/top_level.txt
uber_compose-2.1.4.dist-info/RECORD
