Metadata-Version: 2.4
Name: uber-compose
Version: 2.1.4
Summary: docker compose testing env orchestrator
Home-page: https://github.com/ko10ok/uber-compose
Author: Yuriy Sagitov
Author-email: pro100.ko10ok@gmail.com
License: Apache-2.0
Classifier: License :: OSI Approved :: Apache Software License
Classifier: Programming Language :: Python :: 3.10
Classifier: Programming Language :: Python :: 3.11
Classifier: Programming Language :: Python :: 3.12
Classifier: Programming Language :: Python :: 3.13
Classifier: Programming Language :: Python :: 3.14
Requires-Python: >=3.10.0
License-File: LICENSE
Requires-Dist: vedro<2.0,>=1.10
Requires-Dist: PyYAML<6.1,>=6.0.1
Requires-Dist: rtry<2.0,>=1.4.0
Requires-Dist: rich<16.0,>=11.0
Dynamic: author
Dynamic: author-email
Dynamic: classifier
Dynamic: description
Dynamic: description-content-type
Dynamic: home-page
Dynamic: license
Dynamic: license-file
Dynamic: requires-dist
Dynamic: requires-python
Dynamic: summary
